Workbook

Sheet 📊 Dashboard
B1: 💰 GESTOR DE FINANZAS PERSONALES
B2: Actualizado: 23/05/2026 | Año 2026
B4: 💼 INGRESOS MES | E4: 💸 GASTOS MES | H4: 💰 SALDO MES | K4: 📈 AHORRO %
B5: =SUMIF(Transacciones!E:E,"Ingresos",Transacciones!C:C) | E5: =SUMIF(Transacciones!E:E,"<>Ingresos",Transacciones!C:C) | H5: =B5-E5 | K5: =IF(B5>0,H5/B5,0)
B6: Este mes | E6: Este mes | H6: Este mes | K6: Este mes
B8: 📊 GASTOS POR CATEGORÍA | I8: 📅 EVOLUCIÓN MENSUAL
B9: Categoría | C9: Gasto (€) | D9: % Total | E9: Presupuesto | F9: Estado
B10: Comida | C10: =SUMIF(Transacciones!E:E,"Comida",Transacciones!C:C) | D10: =IF(E5>0,C10/E5,0) | E10: 300 | F10: =IF(C10<=E10,"✅ OK","⚠️ Excedido")
B11: Hogar | C11: =SUMIF(Transacciones!E:E,"Hogar",Transacciones!C:C) | D11: =IF(E5>0,C11/E5,0) | E11: 700 | F11: =IF(C11<=E11,"✅ OK","⚠️ Excedido")
B12: Transporte | C12: =SUMIF(Transacciones!E:E,"Transporte",Transacciones!C:C) | D12: =IF(E5>0,C12/E5,0) | E12: 100 | F12: =IF(C12<=E12,"✅ OK","⚠️ Excedido")
B13: Salud | C13: =SUMIF(Transacciones!E:E,"Salud",Transacciones!C:C) | D13: =IF(E5>0,C13/E5,0) | E13: 80 | F13: =IF(C13<=E13,"✅ OK","⚠️ Excedido")
B14: Ocio | C14: =SUMIF(Transacciones!E:E,"Ocio",Transacciones!C:C) | D14: =IF(E5>0,C14/E5,0) | E14: 150 | F14: =IF(C14<=E14,"✅ OK","⚠️ Excedido")
B15: Inversiones | C15: =SUMIF(Transacciones!E:E,"Inversiones",Transacciones!C:C) | D15: =IF(E5>0,C15/E5,0) | E15: 200 | F15: =IF(C15<=E15,"✅ OK","⚠️ Excedido")
B16: Trabajo | C16: =SUMIF(Transacciones!E:E,"Trabajo",Transacciones!C:C) | D16: =IF(E5>0,C16/E5,0) | E16: 100 | F16: =IF(C16<=E16,"✅ OK","⚠️ Excedido")
B17: Otros | C17: =SUMIF(Transacciones!E:E,"Otros",Transacciones!C:C) | D17: =IF(E5>0,C17/E5,0) | E17: 100 | F17: =IF(C17<=E17,"✅ OK","⚠️ Excedido")
B18: TOTAL | C18: =SUM(C10:C17)

Sheet Transacciones
B1: 📝 REGISTRO DE TRANSACCIONES
B2: Introduce tus ingresos y gastos aquí. La app web los añade automáticamente.
B4: Descripción | C4: Monto (€) | D4: Fecha | E4: Categoría | F4: Tipo | G4: Mes | H4: Notas
B5: Salario enero | C5: 1500 | D5: 01/01/2026 | E5: Ingresos | F5: Ingreso | G5: Enero | H5: Nómina mensual
B6: Mercadona | C6: 85 | D6: 02/01/2026 | E6: Comida | F6: Gasto | G6: Enero | H6: Compra semanal
B7: Alquiler piso | C7: 650 | D7: 03/01/2026 | E7: Hogar | F7: Gasto | G7: Enero | H7: Mensualidad
B8: Gasolina | C8: 48 | D8: 05/01/2026 | E8: Transporte | F8: Gasto | G8: Enero | H8: Repostaje
B9: Netflix | C9: 12.99 | D9: 06/01/2026 | E9: Ocio | F9: Gasto | G9: Enero | H9: Suscripción
B10: Farmacia | C10: 22 | D10: 08/01/2026 | E10: Salud | F10: Gasto | G10: Enero | H10: Medicamentos
B11: Luz + Agua | C11: 90 | D11: 10/01/2026 | E11: Hogar | F11: Gasto | G11: Enero | H11: Facturas
B12: Gym | C12: 35 | D12: 10/01/2026 | E12: Salud | F12: Gasto | G12: Enero | H12: Cuota mensual
B13: Bolsa - ETF | C13: 200 | D13: 15/01/2026 | E13: Inversiones | F13: Gasto | G13: Enero | H13: Aportación indexada
B14: Café bar | C14: 3.5 | D14: 16/01/2026 | E14: Comida | F14: Gasto | G14: Enero | H14: Desayuno
B15: Curso online | C15: 49 | D15: 20/01/2026 | E15: Trabajo | F15: Gasto | G15: Enero | H15: Formación
B16: Wifi fibra | C16: 35 | D16: 22/01/2026 | E16: Hogar | F16: Gasto | G16: Enero | H16: Factura Movistar
... B18: Cena restaurante | C18: 28 | D18: 25/01/2026 | E18: Comida | F18: Gasto | G18: Enero | H18: Cena con amigos
B69: 💡 Las nuevas filas se añaden automáticamente desde la app web. También puedes escribir aquí directamente.

Sheet 📅 Resumen Mensual
B1: 📅 RESUMEN MENSUAL — Año 2026
C3: Ene | D3: Feb | E3: Mar | F3: Abr | G3: May | H3: Jun | I3: Jul | J3: Ago | K3: Sep | L3: Oct | M3: Nov | N3: Dic | P3: TOTAL
B4: 💼 Ingresos Totales | C4: =SUMPRODUCT((Transacciones!G:G="Enero")*(Transacciones!E:E="Ingresos"),Transacciones!C:C) | D4: =SUMPRODUCT((Transacciones!G:G="Febrero")*(Transacciones!E:E="Ingresos"),Transacciones!C:C) | E4: =SUMPRODUCT((Transacciones!G:G="Marzo")*(Transacciones!E:E="Ingresos"),Transacciones!C:C) | F4: =SUMPRODUCT((Transacciones!G:G="Abril")*(Transacciones!E:E="Ingresos"),Transacciones!C:C) | G4: =SUMPRODUCT((Transacciones!G:G="Mayo")*(Transacciones!E:E="Ingresos"),Transacciones!C:C) | H4: =SUMPRODUCT((Transacciones!G:G="Junio")*(Transacciones!E:E="Ingresos"),Transacciones!C:C) | I4: =SUMPRODUCT((Transacciones!G:G="Julio")*(Transacciones!E:E="Ingresos"),Transacciones!C:C) | J4: =SUMPRODUCT((Transacciones!G:G="Agosto")*(Transacciones!E:E="Ingresos"),Transacciones!C:C) | K4: =SUMPRODUCT((Transacciones!G:G="Septiembre")*(Transacciones!E:E="Ingresos"),Transacciones!C:C) | L4: =SUMPRODUCT((Transacciones!G:G="Octubre")*(Transacciones!E:E="Ingresos"),Transacciones!C:C) | M4: =SUMPRODUCT((Transacciones!G:G="Noviembre")*(Transacciones!E:E="Ingresos"),Transacciones!C:C) | N4: =SUMPRODUCT((Transacciones!G:G="Diciembre")*(Transacciones!E:E="Ingresos"),Transacciones!C:C) | P4: =SUM(C4:N4)
B5: → Comida | C5: =SUMPRODUCT((Transacciones!G:G="Enero")*(Transacciones!E:E="Comida"),Transacciones!C:C) | D5: =SUMPRODUCT((Transacciones!G:G="Febrero")*(Transacciones!E:E="Comida"),Transacciones!C:C) | E5: =SUMPRODUCT((Transacciones!G:G="Marzo")*(Transacciones!E:E="Comida"),Transacciones!C:C) | F5: =SUMPRODUCT((Transacciones!G:G="Abril")*(Transacciones!E:E="Comida"),Transacciones!C:C) | G5: =SUMPRODUCT((Transacciones!G:G="Mayo")*(Transacciones!E:E="Comida"),Transacciones!C:C) | H5: =SUMPRODUCT((Transacciones!G:G="Junio")*(Transacciones!E:E="Comida"),Transacciones!C:C) | I5: =SUMPRODUCT((Transacciones!G:G="Julio")*(Transacciones!E:E="Comida"),Transacciones!C:C) | J5: =SUMPRODUCT((Transacciones!G:G="Agosto")*(Transacciones!E:E="Comida"),Transacciones!C:C) | K5: =SUMPRODUCT((Transacciones!G:G="Septiembre")*(Transacciones!E:E="Comida"),Transacciones!C:C) | L5: =SUMPRODUCT((Transacciones!G:G="Octubre")*(Transacciones!E:E="Comida"),Transacciones!C:C) | M5: =SUMPRODUCT((Transacciones!G:G="Noviembre")*(Transacciones!E:E="Comida"),Transacciones!C:C) | N5: =SUMPRODUCT((Transacciones!G:G="Diciembre")*(Transacciones!E:E="Comida"),Transacciones!C:C) | P5: =SUM(C5:N5)
B6: → Hogar | C6: =SUMPRODUCT((Transacciones!G:G="Enero")*(Transacciones!E:E="Hogar"),Transacciones!C:C) | D6: =SUMPRODUCT((Transacciones!G:G="Febrero")*(Transacciones!E:E="Hogar"),Transacciones!C:C) | E6: =SUMPRODUCT((Transacciones!G:G="Marzo")*(Transacciones!E:E="Hogar"),Transacciones!C:C) | F6: =SUMPRODUCT((Transacciones!G:G="Abril")*(Transacciones!E:E="Hogar"),Transacciones!C:C) | G6: =SUMPRODUCT((Transacciones!G:G="Mayo")*(Transacciones!E:E="Hogar"),Transacciones!C:C) | H6: =SUMPRODUCT((Transacciones!G:G="Junio")*(Transacciones!E:E="Hogar"),Transacciones!C:C) | I6: =SUMPRODUCT((Transacciones!G:G="Julio")*(Transacciones!E:E="Hogar"),Transacciones!C:C) | J6: =SUMPRODUCT((Transacciones!G:G="Agosto")*(Transacciones!E:E="Hogar"),Transacciones!C:C) | K6: =SUMPRODUCT((Transacciones!G:G="Septiembre")*(Transacciones!E:E="Hogar"),Transacciones!C:C) | L6: =SUMPRODUCT((Transacciones!G:G="Octubre")*(Transacciones!E:E="Hogar"),Transacciones!C:C) | M6: =SUMPRODUCT((Transacciones!G:G="Noviembre")*(Transacciones!E:E="Hogar"),Transacciones!C:C) | N6: =SUMPRODUCT((Transacciones!G:G="Diciembre")*(Transacciones!E:E="Hogar"),Transacciones!C:C) | P6: =SUM(C6:N6)
B7: → Transporte | C7: =SUMPRODUCT((Transacciones!G:G="Enero")*(Transacciones!E:E="Transporte"),Transacciones!C:C) | D7: =SUMPRODUCT((Transacciones!G:G="Febrero")*(Transacciones!E:E="Transporte"),Transacciones!C:C) | E7: =SUMPRODUCT((Transacciones!G:G="Marzo")*(Transacciones!E:E="Transporte"),Transacciones!C:C) | F7: =SUMPRODUCT((Transacciones!G:G="Abril")*(Transacciones!E:E="Transporte"),Transacciones!C:C) | G7: =SUMPRODUCT((Transacciones!G:G="Mayo")*(Transacciones!E:E="Transporte"),Transacciones!C:C) | H7: =SUMPRODUCT((Transacciones!G:G="Junio")*(Transacciones!E:E="Transporte"),Transacciones!C:C) | I7: =SUMPRODUCT((Transacciones!G:G="Julio")*(Transacciones!E:E="Transporte"),Transacciones!C:C) | J7: =SUMPRODUCT((Transacciones!G:G="Agosto")*(Transacciones!E:E="Transporte"),Transacciones!C:C) | K7: =SUMPRODUCT((Transacciones!G:G="Septiembre")*(Transacciones!E:E="Transporte"),Transacciones!C:C) | L7: =SUMPRODUCT((Transacciones!G:G="Octubre")*(Transacciones!E:E="Transporte"),Transacciones!C:C) | M7: =SUMPRODUCT((Transacciones!G:G="Noviembre")*(Transacciones!E:E="Transporte"),Transacciones!C:C) | N7: =SUMPRODUCT((Transacciones!G:G="Diciembre")*(Transacciones!E:E="Transporte"),Transacciones!C:C) | P7: =SUM(C7:N7)
B8: → Salud | C8: =SUMPRODUCT((Transacciones!G:G="Enero")*(Transacciones!E:E="Salud"),Transacciones!C:C) | D8: =SUMPRODUCT((Transacciones!G:G="Febrero")*(Transacciones!E:E="Salud"),Transacciones!C:C) | E8: =SUMPRODUCT((Transacciones!G:G="Marzo")*(Transacciones!E:E="Salud"),Transacciones!C:C) | F8: =SUMPRODUCT((Transacciones!G:G="Abril")*(Transacciones!E:E="Salud"),Transacciones!C:C) | G8: =SUMPRODUCT((Transacciones!G:G="Mayo")*(Transacciones!E:E="Salud"),Transacciones!C:C) | H8: =SUMPRODUCT((Transacciones!G:G="Junio")*(Transacciones!E:E="Salud"),Transacciones!C:C) | I8: =SUMPRODUCT((Transacciones!G:G="Julio")*(Transacciones!E:E="Salud"),Transacciones!C:C) | J8: =SUMPRODUCT((Transacciones!G:G="Agosto")*(Transacciones!E:E="Salud"),Transacciones!C:C) | K8: =SUMPRODUCT((Transacciones!G:G="Septiembre")*(Transacciones!E:E="Salud"),Transacciones!C:C) | L8: =SUMPRODUCT((Transacciones!G:G="Octubre")*(Transacciones!E:E="Salud"),Transacciones!C:C) | M8: =SUMPRODUCT((Transacciones!G:G="Noviembre")*(Transacciones!E:E="Salud"),Transacciones!C:C) | N8: =SUMPRODUCT((Transacciones!G:G="Diciembre")*(Transacciones!E:E="Salud"),Transacciones!C:C) | P8: =SUM(C8:N8)
B9: → Ocio | C9: =SUMPRODUCT((Transacciones!G:G="Enero")*(Transacciones!E:E="Ocio"),Transacciones!C:C) | D9: =SUMPRODUCT((Transacciones!G:G="Febrero")*(Transacciones!E:E="Ocio"),Transacciones!C:C) | E9: =SUMPRODUCT((Transacciones!G:G="Marzo")*(Transacciones!E:E="Ocio"),Transacciones!C:C) | F9: =SUMPRODUCT((Transacciones!G:G="Abril")*(Transacciones!E:E="Ocio"),Transacciones!C:C) | G9: =SUMPRODUCT((Transacciones!G:G="Mayo")*(Transacciones!E:E="Ocio"),Transacciones!C:C) | H9: =SUMPRODUCT((Transacciones!G:G="Junio")*(Transacciones!E:E="Ocio"),Transacciones!C:C) | I9: =SUMPRODUCT((Transacciones!G:G="Julio")*(Transacciones!E:E="Ocio"),Transacciones!C:C) | J9: =SUMPRODUCT((Transacciones!G:G="Agosto")*(Transacciones!E:E="Ocio"),Transacciones!C:C) | K9: =SUMPRODUCT((Transacciones!G:G="Septiembre")*(Transacciones!E:E="Ocio"),Transacciones!C:C) | L9: =SUMPRODUCT((Transacciones!G:G="Octubre")*(Transacciones!E:E="Ocio"),Transacciones!C:C) | M9: =SUMPRODUCT((Transacciones!G:G="Noviembre")*(Transacciones!E:E="Ocio"),Transacciones!C:C) | N9: =SUMPRODUCT((Transacciones!G:G="Diciembre")*(Transacciones!E:E="Ocio"),Transacciones!C:C) | P9: =SUM(C9:N9)
B10: → Inversiones | C10: =SUMPRODUCT((Transacciones!G:G="Enero")*(Transacciones!E:E="Inversiones"),Transacciones!C:C) | D10: =SUMPRODUCT((Transacciones!G:G="Febrero")*(Transacciones!E:E="Inversiones"),Transacciones!C:C) | E10: =SUMPRODUCT((Transacciones!G:G="Marzo")*(Transacciones!E:E="Inversiones"),Transacciones!C:C) | F10: =SUMPRODUCT((Transacciones!G:G="Abril")*(Transacciones!E:E="Inversiones"),Transacciones!C:C) | G10: =SUMPRODUCT((Transacciones!G:G="Mayo")*(Transacciones!E:E="Inversiones"),Transacciones!C:C) | H10: =SUMPRODUCT((Transacciones!G:G="Junio")*(Transacciones!E:E="Inversiones"),Transacciones!C:C) | I10: =SUMPRODUCT((Transacciones!G:G="Julio")*(Transacciones!E:E="Inversiones"),Transacciones!C:C) | J10: =SUMPRODUCT((Transacciones!G:G="Agosto")*(Transacciones!E:E="Inversiones"),Transacciones!C:C) | K10: =SUMPRODUCT((Transacciones!G:G="Septiembre")*(Transacciones!E:E="Inversiones"),Transacciones!C:C) | L10: =SUMPRODUCT((Transacciones!G:G="Octubre")*(Transacciones!E:E="Inversiones"),Transacciones!C:C) | M10: =SUMPRODUCT((Transacciones!G:G="Noviembre")*(Transacciones!E:E="Inversiones"),Transacciones!C:C) | N10: =SUMPRODUCT((Transacciones!G:G="Diciembre")*(Transacciones!E:E="Inversiones"),Transacciones!C:C) | P10: =SUM(C10:N10)
B11: → Trabajo | C11: =SUMPRODUCT((Transacciones!G:G="Enero")*(Transacciones!E:E="Trabajo"),Transacciones!C:C) | D11: =SUMPRODUCT((Transacciones!G:G="Febrero")*(Transacciones!E:E="Trabajo"),Transacciones!C:C) | E11: =SUMPRODUCT((Transacciones!G:G="Marzo")*(Transacciones!E:E="Trabajo"),Transacciones!C:C) | F11: =SUMPRODUCT((Transacciones!G:G="Abril")*(Transacciones!E:E="Trabajo"),Transacciones!C:C) | G11: =SUMPRODUCT((Transacciones!G:G="Mayo")*(Transacciones!E:E="Trabajo"),Transacciones!C:C) | H11: =SUMPRODUCT((Transacciones!G:G="Junio")*(Transacciones!E:E="Trabajo"),Transacciones!C:C) | I11: =SUMPRODUCT((Transacciones!G:G="Julio")*(Transacciones!E:E="Trabajo"),Transacciones!C:C) | J11: =SUMPRODUCT((Transacciones!G:G="Agosto")*(Transacciones!E:E="Trabajo"),Transacciones!C:C) | K11: =SUMPRODUCT((Transacciones!G:G="Septiembre")*(Transacciones!E:E="Trabajo"),Transacciones!C:C) | L11: =SUMPRODUCT((Transacciones!G:G="Octubre")*(Transacciones!E:E="Trabajo"),Transacciones!C:C) | M11: =SUMPRODUCT((Transacciones!G:G="Noviembre")*(Transacciones!E:E="Trabajo"),Transacciones!C:C) | N11: =SUMPRODUCT((Transacciones!G:G="Diciembre")*(Transacciones!E:E="Trabajo"),Transacciones!C:C) | P11: =SUM(C11:N11)
B12: → Otros | C12: =SUMPRODUCT((Transacciones!G:G="Enero")*(Transacciones!E:E="Otros"),Transacciones!C:C) | D12: =SUMPRODUCT((Transacciones!G:G="Febrero")*(Transacciones!E:E="Otros"),Transacciones!C:C) | E12: =SUMPRODUCT((Transacciones!G:G="Marzo")*(Transacciones!E:E="Otros"),Transacciones!C:C) | F12: =SUMPRODUCT((Transacciones!G:G="Abril")*(Transacciones!E:E="Otros"),Transacciones!C:C) | G12: =SUMPRODUCT((Transacciones!G:G="Mayo")*(Transacciones!E:E="Otros"),Transacciones!C:C) | H12: =SUMPRODUCT((Transacciones!G:G="Junio")*(Transacciones!E:E="Otros"),Transacciones!C:C) | I12: =SUMPRODUCT((Transacciones!G:G="Julio")*(Transacciones!E:E="Otros"),Transacciones!C:C) | J12: =SUMPRODUCT((Transacciones!G:G="Agosto")*(Transacciones!E:E="Otros"),Transacciones!C:C) | K12: =SUMPRODUCT((Transacciones!G:G="Septiembre")*(Transacciones!E:E="Otros"),Transacciones!C:C) | L12: =SUMPRODUCT((Transacciones!G:G="Octubre")*(Transacciones!E:E="Otros"),Transacciones!C:C) | M12: =SUMPRODUCT((Transacciones!G:G="Noviembre")*(Transacciones!E:E="Otros"),Transacciones!C:C) | N12: =SUMPRODUCT((Transacciones!G:G="Diciembre")*(Transacciones!E:E="Otros"),Transacciones!C:C) | P12: =SUM(C12:N12)
B13: 💸 Total Gastos | C13: =C5+C6+C7+C8+C9+C10+C11+C12 | D13: =D5+D6+D7+D8+D9+D10+D11+D12 | E13: =E5+E6+E7+E8+E9+E10+E11+E12 | F13: =F5+F6+F7+F8+F9+F10+F11+F12 | G13: =G5+G6+G7+G8+G9+G10+G11+G12 | H13: =H5+H6+H7+H8+H9+H10+H11+H12 | I13: =I5+I6+I7+I8+I9+I10+I11+I12 | J13: =J5+J6+J7+J8+J9+J10+J11+J12 | ... N13: =N5+N6+N7+N8+N9+N10+N11+N12 | P13: =SUM(C13:N13)
B14: 💰 Saldo Neto | C14: =C4-C13 | D14: =D4-D13 | E14: =E4-E13 | F14: =F4-F13 | G14: =G4-G13 | H14: =H4-H13 | I14: =I4-I13 | J14: =J4-J13 | ... N14: =N4-N13 | P14: =SUM(C14:N14)
B15: 📈 % Ahorro | C15: =IF(C4>0,(C4-C13)/C4,0) | D15: =IF(D4>0,(D4-D13)/D4,0) | E15: =IF(E4>0,(E4-E13)/E4,0) | F15: =IF(F4>0,(F4-F13)/F4,0) | G15: =IF(G4>0,(G4-G13)/G4,0) | H15: =IF(H4>0,(H4-H13)/H4,0) | I15: =IF(I4>0,(I4-I13)/I4,0) | J15: =IF(J4>0,(J4-J13)/J4,0) | ... N15: =IF(N4>0,(N4-N13)/N4,0) | P15: =IF(P4>0,P14/P4,0)

Sheet 🎯 Presupuesto
B1: 🎯 CONTROL DE PRESUPUESTO MENSUAL
B2: 📌 Los valores en AZUL son tus presupuestos. Edítalos a tu gusto.
B4: Categoría | C4: Presupuesto (€) | D4: Gastado (€) | E4: Restante (€) | F4: % Usado | G4: Estado | H4: Barra
B5: Comida | C5: 300 | D5: =SUMIF(Transacciones!E:E,"Comida",Transacciones!C:C) | E5: =C5-D5 | F5: =IF(C5>0,D5/C5,0) | G5: =IF(F5>=1,"🔴 Excedido",IF(F5>=0.8,"🟡 Alerta","🟢 OK")) | H5: =REPT("█",MIN(INT(F5*10),10))&REPT("░",MAX(10-INT(F5*10),0))
B6: Hogar | C6: 700 | D6: =SUMIF(Transacciones!E:E,"Hogar",Transacciones!C:C) | E6: =C6-D6 | F6: =IF(C6>0,D6/C6,0) | G6: =IF(F6>=1,"🔴 Excedido",IF(F6>=0.8,"🟡 Alerta","🟢 OK")) | H6: =REPT("█",MIN(INT(F6*10),10))&REPT("░",MAX(10-INT(F6*10),0))
B7: Transporte | C7: 100 | D7: =SUMIF(Transacciones!E:E,"Transporte",Transacciones!C:C) | E7: =C7-D7 | F7: =IF(C7>0,D7/C7,0) | G7: =IF(F7>=1,"🔴 Excedido",IF(F7>=0.8,"🟡 Alerta","🟢 OK")) | H7: =REPT("█",MIN(INT(F7*10),10))&REPT("░",MAX(10-INT(F7*10),0))
B8: Salud | C8: 80 | D8: =SUMIF(Transacciones!E:E,"Salud",Transacciones!C:C) | E8: =C8-D8 | F8: =IF(C8>0,D8/C8,0) | G8: =IF(F8>=1,"🔴 Excedido",IF(F8>=0.8,"🟡 Alerta","🟢 OK")) | H8: =REPT("█",MIN(INT(F8*10),10))&REPT("░",MAX(10-INT(F8*10),0))
B9: Ocio | C9: 150 | D9: =SUMIF(Transacciones!E:E,"Ocio",Transacciones!C:C) | E9: =C9-D9 | F9: =IF(C9>0,D9/C9,0) | G9: =IF(F9>=1,"🔴 Excedido",IF(F9>=0.8,"🟡 Alerta","🟢 OK")) | H9: =REPT("█",MIN(INT(F9*10),10))&REPT("░",MAX(10-INT(F9*10),0))
B10: Inversiones | C10: 200 | D10: =SUMIF(Transacciones!E:E,"Inversiones",Transacciones!C:C) | E10: =C10-D10 | F10: =IF(C10>0,D10/C10,0) | G10: =IF(F10>=1,"🔴 Excedido",IF(F10>=0.8,"🟡 Alerta","🟢 OK")) | H10: =REPT("█",MIN(INT(F10*10),10))&REPT("░",MAX(10-INT(F10*10),0))
B11: Trabajo | C11: 100 | D11: =SUMIF(Transacciones!E:E,"Trabajo",Transacciones!C:C) | E11: =C11-D11 | F11: =IF(C11>0,D11/C11,0) | G11: =IF(F11>=1,"🔴 Excedido",IF(F11>=0.8,"🟡 Alerta","🟢 OK")) | H11: =REPT("█",MIN(INT(F11*10),10))&REPT("░",MAX(10-INT(F11*10),0))
B12: Otros | C12: 100 | D12: =SUMIF(Transacciones!E:E,"Otros",Transacciones!C:C) | E12: =C12-D12 | F12: =IF(C12>0,D12/C12,0) | G12: =IF(F12>=1,"🔴 Excedido",IF(F12>=0.8,"🟡 Alerta","🟢 OK")) | H12: =REPT("█",MIN(INT(F12*10),10))&REPT("░",MAX(10-INT(F12*10),0))
B13: TOTAL | C13: =SUM(C5:C12) | D13: =SUM(D5:D12) | E13: =C13-D13 | F13: =IF(C13>0,D13/C13,0) | G13: =IF(F13>=1,"🔴 Excedido",IF(F13>=0.8,"🟡 Alerta","🟢 OK"))

Sheet ℹ️ Instrucciones
B1: ℹ️ CÓMO USAR ESTE GESTOR DE FINANZAS
B4: 📱 OPCIÓN 1 — Desde la App Web (recomendado)
B5: 1. Abre la URL de tu app web desde el móvil o PC
B6: 2. Escribe una transacción como 'pan 1euro' o 'gasolina 45€'
B7: 3. La IA la clasifica y añade aquí automáticamente
B9: ✍️ OPCIÓN 2 — Añadir manualmente en esta hoja
B10: 1. Ve a la hoja 'Transacciones'
B11: 2. Rellena: Descripción | Monto | Fecha | Categoría | Tipo | Mes | Notas
B12: 3. El Dashboard se actualiza automáticamente
B14: 📊 HOJAS DEL ARCHIVO
B15: 📊 Dashboard — Resumen visual con KPIs y estado del presupuesto
B16: 📝 Transacciones — Todos los movimientos (la app escribe aquí)
... B31: • Haz una copia del archivo cada mes para tener histórico
